picomc/__init__.py
picomc/__main__.py
picomc/account.py
picomc/config.py
picomc/downloader.py
picomc/errors.py
picomc/instance.py
picomc/launcher.py
picomc/library.py
picomc/logging.py
picomc/msapi.py
picomc/osinfo.py
picomc/rules.py
picomc/utils.py
picomc/version.py
picomc/windows.py
picomc/yggdrasil.py
picomc/cli/__init__.py
picomc/cli/account.py
picomc/cli/config.py
picomc/cli/instance.py
picomc/cli/main.py
picomc/cli/mod.py
picomc/cli/play.py
picomc/cli/utils.py
picomc/cli/version.py
picomc/java/SysDump.class
picomc/java/__init__.py
picomc/mod/__init__.py
picomc/mod/curse.py
picomc/mod/fabric.py
picomc/mod/forge.py
picomc/mod/ftb.py
picomc-0.5.1.dist-info/METADATA
picomc-0.5.1.dist-info/WHEEL
picomc-0.5.1.dist-info/entry_points.txt
picomc-0.5.1.dist-info/licenses/LICENSE
picomc-0.5.1.dist-info/RECORD
